GeshihuaZifuchuanLoudongLiyong/README.md
GeshihuaZifuchuanLoudongLiyong/__init__.py
GeshihuaZifuchuanLoudongLiyong/__main__.py
GeshihuaZifuchuanLoudongLiyong/file.epub
GeshihuaZifuchuanLoudongLiyong/index.html
GeshihuaZifuchuanLoudongLiyong/css/__init__.py
GeshihuaZifuchuanLoudongLiyong/css/annotations.css
GeshihuaZifuchuanLoudongLiyong/css/main.css
GeshihuaZifuchuanLoudongLiyong/css/normalize.css
GeshihuaZifuchuanLoudongLiyong/css/popup.css
GeshihuaZifuchuanLoudongLiyong/font/__init__.py
GeshihuaZifuchuanLoudongLiyong/font/fontello.eot
GeshihuaZifuchuanLoudongLiyong/font/fontello.svg
GeshihuaZifuchuanLoudongLiyong/font/fontello.ttf
GeshihuaZifuchuanLoudongLiyong/font/fontello.woff
GeshihuaZifuchuanLoudongLiyong/img/__init__.py
GeshihuaZifuchuanLoudongLiyong/img/annotator-glyph-sprite.png
GeshihuaZifuchuanLoudongLiyong/img/annotator-icon-sprite.png
GeshihuaZifuchuanLoudongLiyong/img/apple-touch-icon.png
GeshihuaZifuchuanLoudongLiyong/img/cancelfullscreen.png
GeshihuaZifuchuanLoudongLiyong/img/close.png
GeshihuaZifuchuanLoudongLiyong/img/fullscreen.png
GeshihuaZifuchuanLoudongLiyong/img/loader.gif
GeshihuaZifuchuanLoudongLiyong/img/menu-icon.png
GeshihuaZifuchuanLoudongLiyong/img/save.png
GeshihuaZifuchuanLoudongLiyong/img/saved.png
GeshihuaZifuchuanLoudongLiyong/img/settings-s.png
GeshihuaZifuchuanLoudongLiyong/img/settings.png
GeshihuaZifuchuanLoudongLiyong/img/star.png
GeshihuaZifuchuanLoudongLiyong/js/__init__.py
GeshihuaZifuchuanLoudongLiyong/js/epub.js
GeshihuaZifuchuanLoudongLiyong/js/epub.min.js
GeshihuaZifuchuanLoudongLiyong/js/epub.min.map
GeshihuaZifuchuanLoudongLiyong/js/hooks.min.js
GeshihuaZifuchuanLoudongLiyong/js/hooks.min.map
GeshihuaZifuchuanLoudongLiyong/js/reader.js
GeshihuaZifuchuanLoudongLiyong/js/reader.js.map
GeshihuaZifuchuanLoudongLiyong/js/reader.min.js
GeshihuaZifuchuanLoudongLiyong/js/reader.min.map
GeshihuaZifuchuanLoudongLiyong/js/hooks/__init__.py
GeshihuaZifuchuanLoudongLiyong/js/hooks/extensions/__init__.py
geshihua_zifuchuan_loudong_liyong-2024.3.2.0.dist-info/METADATA
geshihua_zifuchuan_loudong_liyong-2024.3.2.0.dist-info/WHEEL
geshihua_zifuchuan_loudong_liyong-2024.3.2.0.dist-info/entry_points.txt
geshihua_zifuchuan_loudong_liyong-2024.3.2.0.dist-info/top_level.txt
geshihua_zifuchuan_loudong_liyong-2024.3.2.0.dist-info/RECORD
